easyappmaker/__init__.py
easyappmaker/alarmapp.py
easyappmaker/browserapp.py
easyappmaker/utils.py
easyappmaker-1.0.0.dist-info/METADATA
easyappmaker-1.0.0.dist-info/WHEEL
easyappmaker-1.0.0.dist-info/top_level.txt
easyappmaker-1.0.0.dist-info/RECORD
