Metadata-Version: 2.4
Name: easyappmaker
Version: 1.0.0
Summary: Personal Python apps: alarmapp, browserapp, and more.
Author: Jay Barua
Requires-Python: >=3.10
Requires-Dist: PyQt5>=5.15
Requires-Dist: playsound>=1.2.2
Dynamic: author
Dynamic: requires-dist
Dynamic: requires-python
Dynamic: summary
